{
  "message": null,
  "success": true,
  "totalProperty": 3,
  "results": [
    {
      "iconCls": null,
      "dataTypeId": null,
      "id": "43",
      "text": null,
      "leaf": false,
      "node": null,
      "start": null,
      "creater": "guest1",
      "limit": null,
      "createtime": 1467289401000,
      "updateStatus": null,
      "datatype": "字符串",
      "isnewest": 1,
      "datatypename": "体积",
      "datatypecode": "1467289401531",
      "userid": "2",
      "checkstr": null,
      "delistJson": null,
      "rank": 8,
      "version": 9,
      "icon": null,
      "description": null,
      "status": 2
    },
    {
      "iconCls": null,
      "dataTypeId": null,
      "id": "32",
      "text": null,
      "leaf": false,
      "node": null,
      "start": null,
      "creater": "guest1",
      "limit": null,
      "createtime": 1406508186000,
      "updateStatus": null,
      "datatype": "字符串",
      "isnewest": 1,
      "datatypename": "x",
      "datatypecode": "1406508186373",
      "userid": "2",
      "checkstr": null,
      "delistJson": null,
      "rank": 8,
      "version": 9,
      "icon": null,
      "description": null,
      "status": 2
    },
    {
      "iconCls": null,
      "dataTypeId": null,
      "id": "35",
      "text": null,
      "leaf": false,
      "node": null,
      "start": null,
      "creater": "guest1",
      "limit": null,
      "createtime": 1406357292000,
      "updateStatus": null,
      "datatype": "字符串",
      "isnewest": 1,
      "datatypename": "新建物理类型",
      "datatypecode": "1406357292379",
      "userid": "2",
      "checkstr": null,
      "delistJson": null,
      "rank": 8,
      "version": 4,
      "icon": null,
      "description": null,
      "status": 2
    }
  ]
}